mcp_conceptual/__init__.py
mcp_conceptual/client.py
mcp_conceptual/key_manager.py
mcp_conceptual/models.py
mcp_conceptual/server.py
mcp_conceptual/tools/__init__.py
mcp_conceptual/tools/admin.py
mcp_conceptual/tools/creatives.py
mcp_conceptual/tools/crm.py
mcp_conceptual/tools/keywords.py
mcp_conceptual/tools/metrics.py
mcp_conceptual-0.4.0.dist-info/licenses/LICENSE
mcp_conceptual-0.4.0.dist-info/METADATA
mcp_conceptual-0.4.0.dist-info/WHEEL
mcp_conceptual-0.4.0.dist-info/entry_points.txt
mcp_conceptual-0.4.0.dist-info/top_level.txt
mcp_conceptual-0.4.0.dist-info/RECORD
